README.txt
setup.cfg
setup.py
docs/HISTORY.txt
docs/INSTALL.txt
docs/LICENSE.GPL
docs/LICENSE.txt
kupu/__init__.py
kupu.mashups.egg-info/PKG-INFO
kupu.mashups.egg-info/SOURCES.txt
kupu.mashups.egg-info/dependency_links.txt
kupu.mashups.egg-info/entry_points.txt
kupu.mashups.egg-info/namespace_packages.txt
kupu.mashups.egg-info/not-zip-safe
kupu.mashups.egg-info/requires.txt
kupu.mashups.egg-info/top_level.txt
kupu/mashups/CHANGELOG
kupu/mashups/README.txt
kupu/mashups/__init__.py
kupu/mashups/config.py
kupu/mashups/configure.zcml
kupu/mashups/profiles.zcml
kupu/mashups/skins.zcml
kupu/mashups/version.txt
kupu/mashups/browser/BeautifulSoup.py
kupu/mashups/browser/__init__.py
kupu/mashups/browser/configure.zcml
kupu/mashups/browser/wikipediamashup.py
kupu/mashups/browser/templates/wikiarticle.pt
kupu/mashups/profiles/default/cssregistry.xml
kupu/mashups/profiles/default/jsregistry.xml
kupu/mashups/profiles/default/skins.xml
kupu/mashups/skins/kupumashups/jsapi.js
kupu/mashups/skins/kupumashups/kupu_wysiwyg_support.html
kupu/mashups/skins/kupumashups/kupumashups_drawers.js
kupu/mashups/skins/kupumashups/kupumashups_init.js
kupu/mashups/skins/kupumashups/kupumashups_popup.js
kupu/mashups/skins/kupumashups/kupumashups_tools.js
kupu/mashups/skins/kupumashups_images/google.png
kupu/mashups/skins/kupumashups_images/google.png.metadata
kupu/mashups/skins/kupumashups_images/loading.gif
kupu/mashups/skins/kupumashups_images/maps.png
kupu/mashups/skins/kupumashups_images/maps.png.metadata
kupu/mashups/skins/kupumashups_images/wikipedia.png
kupu/mashups/skins/kupumashups_images/wikipedia.png.metadata
kupu/mashups/skins/kupumashups_styles/kupumashups_styles.css
kupu/mashups/tests/__init__.py
kupu/mashups/tests/base.py
kupu/mashups/tests/testWikipediaMashup.py