Metadata-Version: 1.0
Name: kupu.mashups
Version: 0.2dev-r81592
Summary: UNKNOWN
Home-page: http://svn.plone.org/svn/collective/kupu,mashups
Author: Matias Bordese
Author-email: mbordese@gmail.com
License: GPL
Platform: UNKNOWN
Classifier: Framework :: Plone
Classifier: Programming Language :: Python
Classifier: Topic :: Software Development :: Libraries :: Python Modules
